RedisKaifaYunweiShijianZhinan/README.md
RedisKaifaYunweiShijianZhinan/__init__.py
RedisKaifaYunweiShijianZhinan/__main__.py
RedisKaifaYunweiShijianZhinan/file.epub
RedisKaifaYunweiShijianZhinan/index.html
RedisKaifaYunweiShijianZhinan/css/__init__.py
RedisKaifaYunweiShijianZhinan/css/annotations.css
RedisKaifaYunweiShijianZhinan/css/main.css
RedisKaifaYunweiShijianZhinan/css/normalize.css
RedisKaifaYunweiShijianZhinan/css/popup.css
RedisKaifaYunweiShijianZhinan/font/__init__.py
RedisKaifaYunweiShijianZhinan/font/fontello.eot
RedisKaifaYunweiShijianZhinan/font/fontello.svg
RedisKaifaYunweiShijianZhinan/font/fontello.ttf
RedisKaifaYunweiShijianZhinan/font/fontello.woff
RedisKaifaYunweiShijianZhinan/img/__init__.py
RedisKaifaYunweiShijianZhinan/img/annotator-glyph-sprite.png
RedisKaifaYunweiShijianZhinan/img/annotator-icon-sprite.png
RedisKaifaYunweiShijianZhinan/img/apple-touch-icon.png
RedisKaifaYunweiShijianZhinan/img/cancelfullscreen.png
RedisKaifaYunweiShijianZhinan/img/close.png
RedisKaifaYunweiShijianZhinan/img/fullscreen.png
RedisKaifaYunweiShijianZhinan/img/loader.gif
RedisKaifaYunweiShijianZhinan/img/menu-icon.png
RedisKaifaYunweiShijianZhinan/img/save.png
RedisKaifaYunweiShijianZhinan/img/saved.png
RedisKaifaYunweiShijianZhinan/img/settings-s.png
RedisKaifaYunweiShijianZhinan/img/settings.png
RedisKaifaYunweiShijianZhinan/img/star.png
RedisKaifaYunweiShijianZhinan/js/__init__.py
RedisKaifaYunweiShijianZhinan/js/epub.js
RedisKaifaYunweiShijianZhinan/js/epub.min.js
RedisKaifaYunweiShijianZhinan/js/epub.min.map
RedisKaifaYunweiShijianZhinan/js/hooks.min.js
RedisKaifaYunweiShijianZhinan/js/hooks.min.map
RedisKaifaYunweiShijianZhinan/js/reader.js
RedisKaifaYunweiShijianZhinan/js/reader.js.map
RedisKaifaYunweiShijianZhinan/js/reader.min.js
RedisKaifaYunweiShijianZhinan/js/reader.min.map
RedisKaifaYunweiShijianZhinan/js/hooks/__init__.py
RedisKaifaYunweiShijianZhinan/js/hooks/extensions/__init__.py
RedisKaifaYunweiShijianZhinan/js/hooks/extensions/highlight.js
redis_kaifa_yunwei_shijian_zhinan-2024.3.3.0.dist-info/METADATA
redis_kaifa_yunwei_shijian_zhinan-2024.3.3.0.dist-info/WHEEL
redis_kaifa_yunwei_shijian_zhinan-2024.3.3.0.dist-info/entry_points.txt
redis_kaifa_yunwei_shijian_zhinan-2024.3.3.0.dist-info/top_level.txt
redis_kaifa_yunwei_shijian_zhinan-2024.3.3.0.dist-info/RECORD
